pyrateshield/LICENSE
pyrateshield/__init__.py
pyrateshield/app.py
pyrateshield/constants.py
pyrateshield/constants.yml
pyrateshield/defaults.yml
pyrateshield/dosemapper.py
pyrateshield/floorplan_and_dosemap.py
pyrateshield/isotopes.yml
pyrateshield/labels.py
pyrateshield/logger.py
pyrateshield/model.py
pyrateshield/model_items.py
pyrateshield/model_sequences.py
pyrateshield/modelitem.py
pyrateshield/observable.py
pyrateshield/shared.py
pyrateshield/gui/__init__.py
pyrateshield/gui/calculator.py
pyrateshield/gui/context_menu.py
pyrateshield/gui/critical_point_controller.py
pyrateshield/gui/dosemap_style.py
pyrateshield/gui/icon.png
pyrateshield/gui/io.py
pyrateshield/gui/isotopes.py
pyrateshield/gui/item_controllers.py
pyrateshield/gui/item_views.py
pyrateshield/gui/main_controller.py
pyrateshield/gui/main_view.py
pyrateshield/gui/mpl_controller.py
pyrateshield/gui/mpl_items_controller.py
pyrateshield/gui/mpl_picker.py
pyrateshield/gui/mpl_view.py
pyrateshield/gui/styles.py
pyrateshield/gui/styles.yml
pyrateshield/pyshield/Radardec4OL.xls
pyrateshield/pyshield/__init__.py
pyrateshield/pyshield/attenuation.xls
pyrateshield/pyshield/buildup.xls
pyrateshield/pyshield/calculator.py
pyrateshield/pyshield/doserates.py
pyrateshield/pyshield/engine.py
pyrateshield/pyshield/isotope.py
pyrateshield/pyshield/tables.py
pyrateshield/radtracer/MCNP.pickle
pyrateshield/radtracer/__init__.py
pyrateshield/radtracer/radtracer.py
pyrateShield-1.0.0.dist-info/LICENSE
pyrateShield-1.0.0.dist-info/METADATA
pyrateShield-1.0.0.dist-info/WHEEL
pyrateShield-1.0.0.dist-info/entry_points.txt
pyrateShield-1.0.0.dist-info/top_level.txt
pyrateShield-1.0.0.dist-info/RECORD
