Metadata-Version: 2.1
Name: pyrateShield
Version: 1.0.0
Summary: Generate radiation-dose maps
Home-page: https://bitbucket.org/MedPhysNL/pyrateShield
Author: Marcel Segbers, Rob van Rooij
Author-email: msegbers@gmail.com
License: GNU GPLv3
Keywords: pyrateShield radiation radiology nuclear medicine
Platform: UNKNOWN
Requires-Python: >=3.8
License-File: LICENSE
Requires-Dist: numpy
Requires-Dist: scipy
Requires-Dist: matplotlib
Requires-Dist: pyqt5
Requires-Dist: pynrrd
Requires-Dist: pyyaml
Requires-Dist: scikit-image
Requires-Dist: imageio
Requires-Dist: pandas
Requires-Dist: psutil
Requires-Dist: xlsxwriter
Requires-Dist: xlrd
Requires-Dist: qtawesome
Requires-Dist: pyperclip
